{"statement": "COMPLETE A FRASE: O GATO ____.", "background": "01-lp-pill_4-nvl_1-1", "layoutID": "bola_ao_alvo_2", "random": true, "steps": [{"txt_ref": [], "img_ref": [], "options": [{"text": "DORME", "img": "", "result": true}, {"text": "AZUL", "img": "", "result": false}, {"text": "CASA", "img": "", "result": false}]}, {"txt_ref": [], "img_ref": [], "options": [{"text": "CORRE", "img": "", "result": true}, {"text": "GRANDE", "img": "", "result": false}, {"text": "SAPATO", "img": "", "result": false}]}]}