{"statement": "ARRASTE AS LETRAS PARA FORMAR MALA.", "background": "01-lp-pill_2-nvl_1-5", "layoutID": "trem_1", "random": false, "steps": [{"txt_ref": [], "img_ref": [], "options": [{"text": "M", "img": "", "result": false}, {"text": "A", "img": "", "result": false}, {"text": "L", "img": "", "result": false}, {"text": "A", "img": "", "result": false}, {"text": "T", "img": "", "result": false}]}, {"txt_ref": [], "img_ref": [], "options": [{"text": "M", "img": "", "result": false}, {"text": "A", "img": "", "result": false}, {"text": "L", "img": "", "result": false}, {"text": "A", "img": "", "result": false}, {"text": "R", "img": "", "result": false}]}]}