{"statement": "PROBLEMA DIGITAL: \"Uma loja vendeu 3 caixas com 12 chocolates cada. Depois vendeu mais 10 chocolates.\" ENUNCIADO: QUANTOS CHOCOLATES FORAM VENDIDOS AO TODO?", "background": "05-lp-pill_4-nvl_2-1", "layoutID": "bola_ao_alvo_2", "random": true, "steps": [{"txt_ref": [], "img_ref": [], "options": [{"text": "46", "img": "", "result": true}, {"text": "36", "img": "", "result": false}, {"text": "22", "img": "", "result": false}]}, {"txt_ref": [], "img_ref": [], "options": [{"text": "(3 x 12) + 10 = 46", "img": "", "result": true}, {"text": "3 + 12 + 10 = 25", "img": "", "result": false}, {"text": "12 + 10 = 22", "img": "", "result": false}]}]}