{"statement": "TEXTO DIGITAL: \"O crescimento da população pode aumentar a necessidade de escolas, hospitais e transporte.\" ENUNCIADO: O QUE PODE ACONTECER QUANDO A POPULAÇÃO CRESCE?", "background": "05-lp-pill_7-nvl_2-5", "layoutID": "bola_ao_alvo_2", "random": true, "steps": [{"txt_ref": [], "img_ref": [], "options": [{"text": "AUMENTA A NECESSIDADE DE SERVIÇOS", "img": "", "result": true}, {"text": "DIMINUI AS CIDADES", "img": "", "result": false}, {"text": "NÃO MUDA NADA", "img": "", "result": false}]}, {"txt_ref": [], "img_ref": [], "options": [{"text": "MAIS ESCOLAS E HOSPITAIS", "img": "", "result": true}, {"text": "MENOS MORADIAS", "img": "", "result": false}, {"text": "MENOS TRANSPORTE", "img": "", "result": false}]}]}