{"statement": "COMPLETE COM PONTO DE INTERROGAÇÃO: ONDE ESTÁ O LIVRO__", "background": "04-lp-pill_3-nvl_2-2", "layoutID": "bola_ao_alvo_2", "random": true, "steps": [{"txt_ref": [], "img_ref": [], "options": [{"text": "?", "img": "", "result": true}, {"text": ".", "img": "", "result": false}, {"text": "!", "img": "", "result": false}]}, {"txt_ref": [], "img_ref": [], "options": [{"text": "?", "img": "", "result": true}, {"text": ",", "img": "", "result": false}, {"text": ".", "img": "", "result": false}]}]}