{"statement": "QUAL NÚMERO ESTÁ ENTRE 145 E 147?", "background": "03-lp-pill_4-nvl_2-3", "layoutID": "bola_ao_alvo_2", "random": true, "steps": [{"txt_ref": [], "img_ref": [], "options": [{"text": "146", "img": "", "result": true}, {"text": "148", "img": "", "result": false}, {"text": "144", "img": "", "result": false}]}, {"txt_ref": [], "img_ref": [], "options": [{"text": "ENTRE 208 E 210 É 209", "img": "", "result": true}, {"text": "211", "img": "", "result": false}, {"text": "207", "img": "", "result": false}]}]}