{"statement": "QUAL ANIMAL VIVE NA ÁGUA?", "background": "02-lp-pill_8-nvl_1-2", "layoutID": "bola_ao_alvo_2", "random": true, "steps": [{"txt_ref": [], "img_ref": [], "options": [{"text": "PEIXE", "img": "", "result": true}, {"text": "CAVALO", "img": "", "result": false}, {"text": "GATO", "img": "", "result": false}]}, {"txt_ref": [], "img_ref": [], "options": [{"text": "TUBARÃO", "img": "", "result": true}, {"text": "VACA", "img": "", "result": false}, {"text": "LEÃO", "img": "", "result": false}]}]}