{"statement": "TEXTO DIGITAL: \"As atividades econômicas ajudam a gerar empregos.\" ENUNCIADO: POR QUE AS ATIVIDADES ECONÔMICAS SÃO IMPORTANTES?", "background": "05-ma-pill_8-nvl_2-5", "layoutID": "bola_ao_alvo_2", "random": true, "steps": [{"txt_ref": [], "img_ref": [], "options": [{"text": "GERAM TRABALHO E RENDA", "img": "", "result": true}, {"text": "DIMINUEM A POPULAÇÃO", "img": "", "result": false}, {"text": "ACABAM COM AS CIDADES", "img": "", "result": false}]}, {"txt_ref": [], "img_ref": [], "options": [{"text": "AJUDAM AS PESSOAS A TRABALHAR", "img": "", "result": true}, {"text": "NÃO AJUDAM EM NADA", "img": "", "result": false}, {"text": "PARALISAM A REGIÃO", "img": "", "result": false}]}]}