{"statement": "ARRASTE AS PALAVRAS PARA FORMAR A FRASE.", "background": "01-lp-pill_3-nvl_1-5", "layoutID": "trem_1", "random": false, "steps": [{"txt_ref": [], "img_ref": [], "options": [{"text": "O", "img": "", "result": false}, {"text": "GATO", "img": "", "result": false}, {"text": "DORME", "img": "", "result": false}]}, {"txt_ref": [], "img_ref": [], "options": [{"text": "A", "img": "", "result": false}, {"text": "MENINA", "img": "", "result": false}, {"text": "COME", "img": "", "result": false}, {"text": "BOLO", "img": "", "result": false}]}]}