{"statement": "QUAL É A PRIMEIRA PARTE DA CADEIA ALIMENTAR?", "background": "04-ma-pill_7-nvl_1-4", "layoutID": "bola_ao_alvo_2", "random": true, "steps": [{"txt_ref": [], "img_ref": [], "options": [{"text": "PLANTA", "img": "", "result": true}, {"text": "LEÃO", "img": "", "result": false}, {"text": "COBRA", "img": "", "result": false}]}, {"txt_ref": [], "img_ref": [], "options": [{"text": "ÁRVORE", "img": "", "result": true}, {"text": "TIGRE", "img": "", "result": false}, {"text": "CACHORRO", "img": "", "result": false}]}]}